hessfit/HessFit_dihes.py
hessfit/HessFit_harmonic.py
hessfit/__init__.py
hessfit/average_across_types.py
hessfit/build_4Smart.py
hessfit/change_mmCOM.py
hessfit/fit4dihe.py
hessfit/force_constant_mod.py
hessfit/gau2xyz.py
hessfit/gauScan2com.py
hessfit/get_amass.py
hessfit/get_mm_energy.py
hessfit/log2scan.py
hessfit/log2topol.py
hessfit/main.py
hessfit/parser_gau.py
hessfit/print_top.py
hessfit/readin_opts.py
hessfit/seminario_module.py
hessfit-0.0.11.dist-info/LICENSE
hessfit-0.0.11.dist-info/METADATA
hessfit-0.0.11.dist-info/WHEEL
hessfit-0.0.11.dist-info/entry_points.txt
hessfit-0.0.11.dist-info/top_level.txt
hessfit-0.0.11.dist-info/RECORD
