Metadata-Version: 2.1
Name: hessfit
Version: 0.0.11
License-File: LICENSE
Requires-Dist: numpy
Requires-Dist: scipy
Requires-Dist: pandas
